pytojcamp/__init__.py
pytojcamp/_version.py
pytojcamp/constants.py
pytojcamp/from_dict.py
pytojcamp/from_xy.py
pytojcamp/utils.py
tests/__init__.py
tests/conftest.py
tests/test_from_dict.py
tests/test_from_xy.py
pytojcamp-0.1.0.dist-info/LICENSE
pytojcamp-0.1.0.dist-info/METADATA
pytojcamp-0.1.0.dist-info/WHEEL
pytojcamp-0.1.0.dist-info/top_level.txt
pytojcamp-0.1.0.dist-info/RECORD
