Metadata-Version: 2.1
Name: pytojcamp
Version: 0.1.0
Summary: UNKNOWN
Home-page: UNKNOWN
Author: Kevin M. Jablonka
Author-email: kevin.jablonka@epfl.ch
License: MIT
Platform: UNKNOWN
Classifier: Programming Language :: Python :: 3
Classifier: Programming Language :: Python :: 3.7
Classifier: Intended Audience :: Science/Research
Classifier: License :: OSI Approved :: MIT License
Classifier: Operating System :: OS Independent
Classifier: Topic :: Scientific/Engineering :: Physics
Classifier: Topic :: Scientific/Engineering :: Chemistry
Classifier: Topic :: Software Development :: Libraries :: Python Modules
Requires-Python: >=3.6
Requires-Dist: numpy (>=1.19)
Provides-Extra: docs
Requires-Dist: Sphinx ; extra == 'docs'
Requires-Dist: sphinx-book-theme ; extra == 'docs'
Requires-Dist: sphinx-autodoc-typehints ; extra == 'docs'
Requires-Dist: sphinx-copybutton ; extra == 'docs'
Provides-Extra: pre-commit
Requires-Dist: pre-commit ; extra == 'pre-commit'
Requires-Dist: black ; extra == 'pre-commit'
Requires-Dist: prospector ; extra == 'pre-commit'
Requires-Dist: pylint ; extra == 'pre-commit'
Requires-Dist: versioneer ; extra == 'pre-commit'
Requires-Dist: isort ; extra == 'pre-commit'
Requires-Dist: gitchangelog ; extra == 'pre-commit'
Provides-Extra: testing
Requires-Dist: pytest ; extra == 'testing'
Requires-Dist: pytest-cov (<2.11) ; extra == 'testing'
